LICENSE
MANIFEST.in
README.md
requirements.txt
requirements_dev.txt
setup.py
tests/__init__.py
tests/base.py
tests/test_actions.py
tests/test_data_received.py
tests/test_on_connect.py
tests/test_pub.py
tests/test_validators.py
txnats/__init__.py
txnats/_meta.py
txnats/actions.py
txnats/backoff.py
txnats/config_state.py
txnats/errors.py
txnats/protocol.py
txnats/resilient.py
txnats/things.py
txnats/validators.py
txnats.egg-info/PKG-INFO
txnats.egg-info/SOURCES.txt
txnats.egg-info/dependency_links.txt
txnats.egg-info/requires.txt
txnats.egg-info/top_level.txt