Metadata-Version: 1.1
Name: txnats
Version: 0.7.5
Summary: NATS messaging system client using Twisted #microservices
Home-page: https://github.com/johnwlockwood/txnats
Author: John W Lockwood IV
Author-email: john.lockwood@workiva.com
License: The MIT License (MIT)
